yt_search/__init__.py
yt_search/errors.py
yt_search/search.py
yt_search-1.1.0.post1.dist-info/LICENSE
yt_search-1.1.0.post1.dist-info/METADATA
yt_search-1.1.0.post1.dist-info/WHEEL
yt_search-1.1.0.post1.dist-info/top_level.txt
yt_search-1.1.0.post1.dist-info/RECORD
