Metadata-Version: 2.1
Name: yt_search
Version: 1.1.0.post1
Summary: Search contents on YouTube.
Home-page: https://github.com/jun50/yt-search
Author: jun50
Author-email: 0001jun50@gmail.com
License: GPLv3
Keywords: YouTube API
Platform: UNKNOWN
Classifier: License :: OSI Approved :: GNU General Public License v3 (GPLv3)
Classifier: Programming Language :: Python :: 3.7
Classifier: Programming Language :: Python :: 3.6
Requires-Python: >=3.6
